LICENSE.txt
MANIFEST.in
README.rst
setup.py
yeti/__init__.py
yeti/default.yml
yeti/engine.py
yeti/module.py
yeti/robot.py
yeti/version.py
yeti.egg-info/PKG-INFO
yeti.egg-info/SOURCES.txt
yeti.egg-info/dependency_links.txt
yeti.egg-info/requires.txt
yeti.egg-info/top_level.txt
yeti/__pycache__/__init__.cpython-34.pyc
yeti/__pycache__/__init__.cpython-35.pyc
yeti/__pycache__/config_manger.cpython-35.pyc
yeti/__pycache__/context.cpython-35.pyc
yeti/__pycache__/engine.cpython-34.pyc
yeti/__pycache__/engine.cpython-35.pyc
yeti/__pycache__/hook_server.cpython-35.pyc
yeti/__pycache__/module.cpython-34.pyc
yeti/__pycache__/module.cpython-35.pyc
yeti/__pycache__/module_loader.cpython-35.pyc
yeti/__pycache__/robot.cpython-34.pyc
yeti/__pycache__/robot.cpython-35.pyc
yeti/__pycache__/version.cpython-34.pyc
yeti/__pycache__/version.cpython-35.pyc
yeti/modules/__init__.py
yeti/modules/gameclock.py
yeti/modules/triggers.py
yeti/modules/__pycache__/__init__.cpython-34.pyc
yeti/modules/__pycache__/__init__.cpython-35.pyc
yeti/modules/__pycache__/datastreamer.cpython-35.pyc
yeti/modules/__pycache__/gameclock.cpython-34.pyc
yeti/modules/__pycache__/gameclock.cpython-35.pyc
yeti/modules/__pycache__/triggers.cpython-35.pyc
yeti/modules/webui/__init__.py
yeti/modules/webui/webui.py
yeti/modules/webui/__pycache__/__init__.cpython-34.pyc
yeti/modules/webui/__pycache__/__init__.cpython-35.pyc
yeti/modules/webui/__pycache__/webui.cpython-34.pyc
yeti/modules/webui/__pycache__/webui.cpython-35.pyc
yeti/modules/webui/resources/FIRSTvert_Reversed.gif
yeti/modules/webui/resources/dashboard.css
yeti/modules/webui/resources/favicon.ico
yeti/modules/webui/resources/index.html
yeti/modules/webui/resources/jquery.min.js
yeti/modules/webui/resources/powered_by_robotpy.png
yeti/modules/webui/resources/script.js
yeti/modules/webui/resources/bootstrap/css/bootstrap-theme.css
yeti/modules/webui/resources/bootstrap/css/bootstrap-theme.css.map
yeti/modules/webui/resources/bootstrap/css/bootstrap-theme.min.css
yeti/modules/webui/resources/bootstrap/css/bootstrap.css
yeti/modules/webui/resources/bootstrap/css/bootstrap.css.map
