Metadata-Version: 1.1
Name: yeti
Version: 2016.0.3
Summary: Yeti
Home-page: https://github.com/Team4819/yeti
Author: Christian Balcom
Author-email: robot.inventor@gmail.com
License: BSD License
Keywords: frc first robotics asyncio
Platform: UNKNOWN
Classifier: Development Status :: 5 - Production/Stable
Classifier: Intended Audience :: Developers
Classifier: Intended Audience :: Education
Classifier: License :: OSI Approved :: BSD License
Classifier: Operating System :: OS Independent
Classifier: Programming Language :: Python :: 3.4
Classifier: Topic :: Scientific/Engineering
